{
  "items": [
    {
      "id": "s1",
      "type": "series",
      "title": "Prison Break",
      "year": 2005,
      "description": "Prison Break suit l'histoire de Michael Scofield, un ingénieur qui se fait délibérément incarcérer dans une prison d'État afin d'en faire évader son frère, condamné à mort pour un crime qu'il n'a pas commis.",
      "poster": "https://fr.web.img6.acsta.net/pictures/17/05/22/16/49/588696.jpg",
      "backdrop": "https://www.themoviedb.org/t/p/original/7w186sl42Qf1eYdkdPFDeWySUxL.jpg",
      "seasons": [
        {
          "number": 1,
          "title": "Saison 1",
          "episodes": [
            {
              "number": 1,
              "title": "Épisode 1",
              "duration": "43:00",
              "description": "Suite de l'évasion de Michael et des tensions à Fox River.",
              "thumbnail": "https://www.themoviedb.org/t/p/w454_and_h254_bestv2/yVa2L8mMjvRoKGrLUJxd0NxIkMy.jpg",
              "link": "https://uqload.cx/yoke7ilgvg2l.html"
            },
            {
              "number": 2,
              "title": "Épisode 2",
              "duration": "43:00",
              "description": "Suite de l'évasion de Michael et des tensions à Fox River.",
              "thumbnail": "https://www.themoviedb.org/t/p/w454_and_h254_bestv2/yVa2L8mMjvRoKGrLUJxd0NxIkMy.jpg",
              "link": "https://uqload.cx/5ny3epdciay9.html"
            },
            {
              "number": 3,
              "title": "Épisode 3",
              "duration": "43:00",
              "description": "Suite de l'évasion de Michael et des tensions à Fox River.",
              "thumbnail": "https://www.themoviedb.org/t/p/w454_and_h254_bestv2/yVa2L8mMjvRoKGrLUJxd0NxIkMy.jpg",
              "link": "https://uqload.cx/5ny3epdciay9.html"
            },
            {
              "number": 4,
              "title": "Épisode 4",
              "duration": "43:00",
              "description": "Suite de l'évasion de Michael et des tensions à Fox River.",
              "thumbnail": "https://www.themoviedb.org/t/p/w454_and_h254_bestv2/yVa2L8mMjvRoKGrLUJxd0NxIkMy.jpg",
              "link": "https://uqload.cx/oye71823d8d7.html"
            },
            {
              "number": 5,
              "title": "Épisode 5",
              "duration": "43:00",
              "description": "Suite de l'évasion de Michael et des tensions à Fox River.",
              "thumbnail": "https://www.themoviedb.org/t/p/w454_and_h254_bestv2/yVa2L8mMjvRoKGrLUJxd0NxIkMy.jpg",
              "link": "https://uqload.cx/jr32og9oklhc.html"
            },
            {
              "number": 6,
              "title": "Épisode 6",
              "duration": "43:00",
              "description": "Suite de l'évasion de Michael et des tensions à Fox River.",
              "thumbnail": "https://www.themoviedb.org/t/p/w454_and_h254_bestv2/yVa2L8mMjvRoKGrLUJxd0NxIkMy.jpg",
              "link": "https://uqload.cx/uo5qobf0hrfx.html"
            },
            {
              "number": 7,
              "title": "Épisode 7",
              "duration": "43:00",
              "description": "Suite de l'évasion de Michael et des tensions à Fox River.",
              "thumbnail": "https://www.themoviedb.org/t/p/w454_and_h254_bestv2/yVa2L8mMjvRoKGrLUJxd0NxIkMy.jpg",
              "link": "https://uqload.cx/h28cyhdkg79u.html"
            },
            {
              "number": 8,
              "title": "Épisode 8",
              "duration": "43:00",
              "description": "Suite de l'évasion de Michael et des tensions à Fox River.",
              "thumbnail": "https://www.themoviedb.org/t/p/w454_and_h254_bestv2/yVa2L8mMjvRoKGrLUJxd0NxIkMy.jpg",
              "link": "https://uqload.cx/metpuq4qthr3.html"
            },
            {
              "number": 9,
              "title": "Épisode 9",
              "duration": "43:00",
              "description": "Suite de l'évasion de Michael et des tensions à Fox River.",
              "thumbnail": "https://www.themoviedb.org/t/p/w454_and_h254_bestv2/yVa2L8mMjvRoKGrLUJxd0NxIkMy.jpg",
              "link": "https://uqload.cx/qgtessawi018.html"
            },
            {
              "number": 10,
              "title": "Épisode 10",
              "duration": "43:00",
              "description": "Suite de l'évasion de Michael et des tensions à Fox River.",
              "thumbnail": "https://www.themoviedb.org/t/p/w454_and_h254_bestv2/yVa2L8mMjvRoKGrLUJxd0NxIkMy.jpg",
              "link": "https://uqload.cx/nex4qj0ce21s.html"
            },
            {
              "number": 11,
              "title": "Épisode 11",
              "duration": "43:00",
              "description": "Suite de l'évasion de Michael et des tensions à Fox River.",
              "thumbnail": "https://www.themoviedb.org/t/p/w454_and_h254_bestv2/yVa2L8mMjvRoKGrLUJxd0NxIkMy.jpg",
              "link": "https://uqload.cx/ey1ypmum3rr5.html"
            },
            {
              "number": 12,
              "title": "Épisode 12",
              "duration": "43:00",
              "description": "Suite de l'évasion de Michael et des tensions à Fox River.",
              "thumbnail": "https://www.themoviedb.org/t/p/w454_and_h254_bestv2/yVa2L8mMjvRoKGrLUJxd0NxIkMy.jpg",
              "link": "https://uqload.cx/lee75ulih5gl.html"
            },
            {
              "number": 13,
              "title": "Épisode 13",
              "duration": "43:00",
              "description": "Suite de l'évasion de Michael et des tensions à Fox River.",
              "thumbnail": "https://www.themoviedb.org/t/p/w454_and_h254_bestv2/yVa2L8mMjvRoKGrLUJxd0NxIkMy.jpg",
              "link": "https://uqload.cx/wafa7plb86o5.html"
            },
            {
              "number": 14,
              "title": "Épisode 14",
              "duration": "43:00",
              "description": "Suite de l'évasion de Michael et des tensions à Fox River.",
              "thumbnail": "https://www.themoviedb.org/t/p/w454_and_h254_bestv2/yVa2L8mMjvRoKGrLUJxd0NxIkMy.jpg",
              "link": "https://uqload.cx/s5sibny6vvqu.html"
            },
            {
              "number": 15,
              "title": "Épisode 15",
              "duration": "43:00",
              "description": "Suite de l'évasion de Michael et des tensions à Fox River.",
              "thumbnail": "https://www.themoviedb.org/t/p/w454_and_h254_bestv2/yVa2L8mMjvRoKGrLUJxd0NxIkMy.jpg",
              "link": "https://uqload.cx/nra4c5brd3fq.html"
            },
            {
              "number": 16,
              "title": "Épisode 16",
              "duration": "43:00",
              "description": "Suite de l'évasion de Michael et des tensions à Fox River.",
              "thumbnail": "https://www.themoviedb.org/t/p/w454_and_h254_bestv2/yVa2L8mMjvRoKGrLUJxd0NxIkMy.jpg",
              "link": "https://uqload.cx/ilyh90ukzsld.html"
            },
            {
              "number": 17,
              "title": "Épisode 17",
              "duration": "43:00",
              "description": "Suite de l'évasion de Michael et des tensions à Fox River.",
              "thumbnail": "https://www.themoviedb.org/t/p/w454_and_h254_bestv2/yVa2L8mMjvRoKGrLUJxd0NxIkMy.jpg",
              "link": "https://uqload.cx/gwjhr95q1p6w.html"
            },
            {
              "number": 18,
              "title": "Épisode 18",
              "duration": "43:00",
              "description": "Suite de l'évasion de Michael et des tensions à Fox River.",
              "thumbnail": "https://www.themoviedb.org/t/p/w454_and_h254_bestv2/yVa2L8mMjvRoKGrLUJxd0NxIkMy.jpg",
              "link": "https://uqload.cx/x7sl6x3p3y81.html"
            },
            {
              "number": 19,
              "title": "Épisode 19",
              "duration": "43:00",
              "description": "Suite de l'évasion de Michael et des tensions à Fox River.",
              "thumbnail": "https://www.themoviedb.org/t/p/w454_and_h254_bestv2/yVa2L8mMjvRoKGrLUJxd0NxIkMy.jpg",
              "link": "https://uqload.cx/joydpj2u3qu4.html"
            },
            {
              "number": 20,
              "title": "Épisode 20",
              "duration": "43:00",
              "description": "Suite de l'évasion de Michael et des tensions à Fox River.",
              "thumbnail": "https://www.themoviedb.org/t/p/w454_and_h254_bestv2/yVa2L8mMjvRoKGrLUJxd0NxIkMy.jpg",
              "link": "https://uqload.cx/o6zm3kt683zr.html"
            },
            {
              "number": 21,
              "title": "Épisode 21",
              "duration": "43:00",
              "description": "Suite de l'évasion de Michael et des tensions à Fox River.",
              "thumbnail": "https://www.themoviedb.org/t/p/w454_and_h254_bestv2/yVa2L8mMjvRoKGrLUJxd0NxIkMy.jpg",
              "link": "https://uqload.cx/05j519xgjnup.html"
            },
            {
              "number": 22,
              "title": "Épisode 22",
              "duration": "43:00",
              "description": "Suite de l'évasion de Michael et des tensions à Fox River.",
              "thumbnail": "https://www.themoviedb.org/t/p/w454_and_h254_bestv2/yVa2L8mMjvRoKGrLUJxd0NxIkMy.jpg",
              "link": "https://uqload.cx/i9d5z4roct5k.html"
            }
          ]
        },
        {
          "number": 2,
          "title": "Saison 2",
          "episodes": [
            {
              "number": 1,
              "title": "Épisode 1",
              "duration": "43:00",
              "description": "Suite de l'évasion de Michael et des tensions à Fox River.",
              "thumbnail": "https://www.themoviedb.org/t/p/w454_and_h254_bestv2/yVa2L8mMjvRoKGrLUJxd0NxIkMy.jpg",
              "link": "https://uqload.cx/xqbjxmeg722b.html"
            },
            {
              "number": 2,
              "title": "Épisode 2",
              "duration": "43:00",
              "description": "Suite de l'évasion de Michael et des tensions à Fox River.",
              "thumbnail": "https://www.themoviedb.org/t/p/w454_and_h254_bestv2/yVa2L8mMjvRoKGrLUJxd0NxIkMy.jpg",
              "link": "https://uqload.cx/lp0s97h7pkgl.html"
            },
            {
              "number": 3,
              "title": "Épisode 3",
              "duration": "43:00",
              "description": "Suite de l'évasion de Michael et des tensions à Fox River.",
              "thumbnail": "https://www.themoviedb.org/t/p/w454_and_h254_bestv2/yVa2L8mMjvRoKGrLUJxd0NxIkMy.jpg",
              "link": "https://uqload.cx/g0su1v780w2j.html"
            },
            {
              "number": 4,
              "title": "Épisode 4",
              "duration": "43:00",
              "description": "Suite de l'évasion de Michael et des tensions à Fox River.",
              "thumbnail": "https://www.themoviedb.org/t/p/w454_and_h254_bestv2/yVa2L8mMjvRoKGrLUJxd0NxIkMy.jpg",
              "link": "https://uqload.cx/lahr7pk3tljf.html"
            },
            {
              "number": 5,
              "title": "Épisode 5",
              "duration": "43:00",
              "description": "Suite de l'évasion de Michael et des tensions à Fox River.",
              "thumbnail": "https://www.themoviedb.org/t/p/w454_and_h254_bestv2/yVa2L8mMjvRoKGrLUJxd0NxIkMy.jpg",
              "link": "https://uqload.cx/2nmjh46k0m4w.html"
            },
            {
              "number": 6,
              "title": "Épisode 6",
              "duration": "43:00",
              "description": "Suite de l'évasion de Michael et des tensions à Fox River.",
              "thumbnail": "https://www.themoviedb.org/t/p/w454_and_h254_bestv2/yVa2L8mMjvRoKGrLUJxd0NxIkMy.jpg",
              "link": "https://uqload.cx/nxxqo52b70yq.html"
            },
            {
              "number": 7,
              "title": "Épisode 7",
              "duration": "43:00",
              "description": "Suite de l'évasion de Michael et des tensions à Fox River.",
              "thumbnail": "https://www.themoviedb.org/t/p/w454_and_h254_bestv2/yVa2L8mMjvRoKGrLUJxd0NxIkMy.jpg",
              "link": "https://uqload.cx/d7fq97ar2392.html"
            },
            {
              "number": 8,
              "title": "Épisode 8",
              "duration": "43:00",
              "description": "Suite de l'évasion de Michael et des tensions à Fox River.",
              "thumbnail": "https://www.themoviedb.org/t/p/w454_and_h254_bestv2/yVa2L8mMjvRoKGrLUJxd0NxIkMy.jpg",
              "link": "https://uqload.cx/x4d7zayk3y1v.html"
            },
            {
              "number": 9,
              "title": "Épisode 9",
              "duration": "43:00",
              "description": "Suite de l'évasion de Michael et des tensions à Fox River.",
              "thumbnail": "https://www.themoviedb.org/t/p/w454_and_h254_bestv2/yVa2L8mMjvRoKGrLUJxd0NxIkMy.jpg",
              "link": "https://uqload.cx/offqklhvo7hw.html"
            },
            {
              "number": 10,
              "title": "Épisode 10",
              "duration": "43:00",
              "description": "Suite de l'évasion de Michael et des tensions à Fox River.",
              "thumbnail": "https://www.themoviedb.org/t/p/w454_and_h254_bestv2/yVa2L8mMjvRoKGrLUJxd0NxIkMy.jpg",
              "link": "https://uqload.cx/l49qxl81oqwy.html"
            },
            {
              "number": 11,
              "title": "Épisode 11",
              "duration": "43:00",
              "description": "Suite de l'évasion de Michael et des tensions à Fox River.",
              "thumbnail": "https://www.themoviedb.org/t/p/w454_and_h254_bestv2/yVa2L8mMjvRoKGrLUJxd0NxIkMy.jpg",
              "link": "https://uqload.cx/m7ifmhrgf9ik.html"
            },
            {
              "number": 12,
              "title": "Épisode 12",
              "duration": "43:00",
              "description": "Suite de l'évasion de Michael et des tensions à Fox River.",
              "thumbnail": "https://www.themoviedb.org/t/p/w454_and_h254_bestv2/yVa2L8mMjvRoKGrLUJxd0NxIkMy.jpg",
              "link": "https://uqload.cx/qfuefw81u8a5.html"
            },
            {
              "number": 13,
              "title": "Épisode 13",
              "duration": "43:00",
              "description": "Suite de l'évasion de Michael et des tensions à Fox River.",
              "thumbnail": "https://www.themoviedb.org/t/p/w454_and_h254_bestv2/yVa2L8mMjvRoKGrLUJxd0NxIkMy.jpg",
              "link": "https://uqload.cx/4ykv5a4g3306.html"
            },
            {
              "number": 14,
              "title": "Épisode 14",
              "duration": "43:00",
              "description": "Suite de l'évasion de Michael et des tensions à Fox River.",
              "thumbnail": "https://www.themoviedb.org/t/p/w454_and_h254_bestv2/yVa2L8mMjvRoKGrLUJxd0NxIkMy.jpg",
              "link": "https://uqload.cx/yp5436mvjeif.html"
            },
            {
              "number": 15,
              "title": "Épisode 15",
              "duration": "43:00",
              "description": "Suite de l'évasion de Michael et des tensions à Fox River.",
              "thumbnail": "https://www.themoviedb.org/t/p/w454_and_h254_bestv2/yVa2L8mMjvRoKGrLUJxd0NxIkMy.jpg",
              "link": "https://uqload.cx/rkm4zsk64wdm.html"
            },
            {
              "number": 16,
              "title": "Épisode 16",
              "duration": "43:00",
              "description": "Suite de l'évasion de Michael et des tensions à Fox River.",
              "thumbnail": "https://www.themoviedb.org/t/p/w454_and_h254_bestv2/yVa2L8mMjvRoKGrLUJxd0NxIkMy.jpg",
              "link": "https://uqload.cx/lo8l8qlr58jo.html"
            },
            {
              "number": 17,
              "title": "Épisode 17",
              "duration": "43:00",
              "description": "Suite de l'évasion de Michael et des tensions à Fox River.",
              "thumbnail": "https://www.themoviedb.org/t/p/w454_and_h254_bestv2/yVa2L8mMjvRoKGrLUJxd0NxIkMy.jpg",
              "link": "https://uqload.cx/275qtlr1dd1p.html"
            },
            {
              "number": 18,
              "title": "Épisode 18",
              "duration": "43:00",
              "description": "Suite de l'évasion de Michael et des tensions à Fox River.",
              "thumbnail": "https://www.themoviedb.org/t/p/w454_and_h254_bestv2/yVa2L8mMjvRoKGrLUJxd0NxIkMy.jpg",
              "link": "https://uqload.cx/slx4qbn68evb.html"
            },
            {
              "number": 19,
              "title": "Épisode 19",
              "duration": "43:00",
              "description": "Suite de l'évasion de Michael et des tensions à Fox River.",
              "thumbnail": "https://www.themoviedb.org/t/p/w454_and_h254_bestv2/yVa2L8mMjvRoKGrLUJxd0NxIkMy.jpg",
              "link": "https://uqload.cx/ivtmqc2wnsha.html"
            },
            {
              "number": 20,
              "title": "Épisode 20",
              "duration": "43:00",
              "description": "Suite de l'évasion de Michael et des tensions à Fox River.",
              "thumbnail": "https://www.themoviedb.org/t/p/w454_and_h254_bestv2/yVa2L8mMjvRoKGrLUJxd0NxIkMy.jpg",
              "link": "https://uqload.cx/9eln8v6vmsvn.html"
            },
            {
              "number": 21,
              "title": "Épisode 21",
              "duration": "43:00",
              "description": "Suite de l'évasion de Michael et des tensions à Fox River.",
              "thumbnail": "https://www.themoviedb.org/t/p/w454_and_h254_bestv2/yVa2L8mMjvRoKGrLUJxd0NxIkMy.jpg",
              "link": "https://uqload.cx/0fwsl0axxv82.html"
            },
            {
              "number": 22,
              "title": "Épisode 22",
              "duration": "43:00",
              "description": "Suite de l'évasion de Michael et des tensions à Fox River.",
              "thumbnail": "https://www.themoviedb.org/t/p/w454_and_h254_bestv2/yVa2L8mMjvRoKGrLUJxd0NxIkMy.jpg",
              "link": "https://uqload.cx/m6rysiupqa74.html"
            }
          ]
        },
        {
          "number": 3,
          "title": "Saison 3",
          "episodes": [
            {
              "number": 1,
              "title": "Épisode 1",
              "duration": "43:00",
              "description": "Suite de l'évasion de Michael et des tensions à Fox River.",
              "thumbnail": "https://www.themoviedb.org/t/p/w454_and_h254_bestv2/yVa2L8mMjvRoKGrLUJxd0NxIkMy.jpg",
              "link": "https://uqload.cx/embed-jr32og9oklhc.html"
            },
            {
              "number": 2,
              "title": "Épisode 2",
              "duration": "43:00",
              "description": "Suite de l'évasion de Michael et des tensions à Fox River.",
              "thumbnail": "https://www.themoviedb.org/t/p/w454_and_h254_bestv2/yVa2L8mMjvRoKGrLUJxd0NxIkMy.jpg",
              "link": "https://uqload.cx/embed-jr32og9oklhc.html"
            },
            {
              "number": 3,
              "title": "Épisode 3",
              "duration": "43:00",
              "description": "Suite de l'évasion de Michael et des tensions à Fox River.",
              "thumbnail": "https://www.themoviedb.org/t/p/w454_and_h254_bestv2/yVa2L8mMjvRoKGrLUJxd0NxIkMy.jpg",
              "link": "https://uqload.cx/embed-jr32og9oklhc.html"
            },
            {
              "number": 4,
              "title": "Épisode 4",
              "duration": "43:00",
              "description": "Suite de l'évasion de Michael et des tensions à Fox River.",
              "thumbnail": "https://www.themoviedb.org/t/p/w454_and_h254_bestv2/yVa2L8mMjvRoKGrLUJxd0NxIkMy.jpg",
              "link": "https://uqload.cx/embed-jr32og9oklhc.html"
            },
            {
              "number": 5,
              "title": "Épisode 5",
              "duration": "43:00",
              "description": "Suite de l'évasion de Michael et des tensions à Fox River.",
              "thumbnail": "https://www.themoviedb.org/t/p/w454_and_h254_bestv2/yVa2L8mMjvRoKGrLUJxd0NxIkMy.jpg",
              "link": "https://uqload.cx/embed-jr32og9oklhc.html"
            },
            {
              "number": 6,
              "title": "Épisode 6",
              "duration": "43:00",
              "description": "Suite de l'évasion de Michael et des tensions à Fox River.",
              "thumbnail": "https://www.themoviedb.org/t/p/w454_and_h254_bestv2/yVa2L8mMjvRoKGrLUJxd0NxIkMy.jpg",
              "link": "https://uqload.cx/embed-jr32og9oklhc.html"
            },
            {
              "number": 7,
              "title": "Épisode 7",
              "duration": "43:00",
              "description": "Suite de l'évasion de Michael et des tensions à Fox River.",
              "thumbnail": "https://www.themoviedb.org/t/p/w454_and_h254_bestv2/yVa2L8mMjvRoKGrLUJxd0NxIkMy.jpg",
              "link": "https://uqload.cx/embed-jr32og9oklhc.html"
            },
            {
              "number": 8,
              "title": "Épisode 8",
              "duration": "43:00",
              "description": "Suite de l'évasion de Michael et des tensions à Fox River.",
              "thumbnail": "https://www.themoviedb.org/t/p/w454_and_h254_bestv2/yVa2L8mMjvRoKGrLUJxd0NxIkMy.jpg",
              "link": "https://uqload.cx/embed-jr32og9oklhc.html"
            },
            {
              "number": 9,
              "title": "Épisode 9",
              "duration": "43:00",
              "description": "Suite de l'évasion de Michael et des tensions à Fox River.",
              "thumbnail": "https://www.themoviedb.org/t/p/w454_and_h254_bestv2/yVa2L8mMjvRoKGrLUJxd0NxIkMy.jpg",
              "link": "https://uqload.cx/embed-jr32og9oklhc.html"
            },
            {
              "number": 10,
              "title": "Épisode 10",
              "duration": "43:00",
              "description": "Suite de l'évasion de Michael et des tensions à Fox River.",
              "thumbnail": "https://www.themoviedb.org/t/p/w454_and_h254_bestv2/yVa2L8mMjvRoKGrLUJxd0NxIkMy.jpg",
              "link": "https://uqload.cx/embed-jr32og9oklhc.html"
            },
            {
              "number": 11,
              "title": "Épisode 11",
              "duration": "43:00",
              "description": "Suite de l'évasion de Michael et des tensions à Fox River.",
              "thumbnail": "https://www.themoviedb.org/t/p/w454_and_h254_bestv2/yVa2L8mMjvRoKGrLUJxd0NxIkMy.jpg",
              "link": "https://uqload.cx/embed-jr32og9oklhc.html"
            },
            {
              "number": 12,
              "title": "Épisode 12",
              "duration": "43:00",
              "description": "Suite de l'évasion de Michael et des tensions à Fox River.",
              "thumbnail": "https://www.themoviedb.org/t/p/w454_and_h254_bestv2/yVa2L8mMjvRoKGrLUJxd0NxIkMy.jpg",
              "link": "https://uqload.cx/embed-jr32og9oklhc.html"
            },
            {
              "number": 13,
              "title": "Épisode 13",
              "duration": "43:00",
              "description": "Suite de l'évasion de Michael et des tensions à Fox River.",
              "thumbnail": "https://www.themoviedb.org/t/p/w454_and_h254_bestv2/yVa2L8mMjvRoKGrLUJxd0NxIkMy.jpg",
              "link": "https://uqload.cx/embed-jr32og9oklhc.html"
            },
            {
              "number": 14,
              "title": "Épisode 14",
              "duration": "43:00",
              "description": "Suite de l'évasion de Michael et des tensions à Fox River.",
              "thumbnail": "https://www.themoviedb.org/t/p/w454_and_h254_bestv2/yVa2L8mMjvRoKGrLUJxd0NxIkMy.jpg",
              "link": "https://uqload.cx/embed-jr32og9oklhc.html"
            }
          ]
        },
        {
          "number": 4,
          "title": "Saison 4",
          "episodes": [
            {
              "number": 1,
              "title": "Épisode 1",
              "duration": "43:00",
              "description": "Suite de l'évasion de Michael et des tensions à Fox River.",
              "thumbnail": "https://www.themoviedb.org/t/p/w454_and_h254_bestv2/yVa2L8mMjvRoKGrLUJxd0NxIkMy.jpg",
              "link": "https://uqload.cx/embed-jr32og9oklhc.html"
            },
            {
              "number": 2,
              "title": "Épisode 2",
              "duration": "43:00",
              "description": "Suite de l'évasion de Michael et des tensions à Fox River.",
              "thumbnail": "https://www.themoviedb.org/t/p/w454_and_h254_bestv2/yVa2L8mMjvRoKGrLUJxd0NxIkMy.jpg",
              "link": "https://uqload.cx/embed-jr32og9oklhc.html"
            },
            {
              "number": 3,
              "title": "Épisode 3",
              "duration": "43:00",
              "description": "Suite de l'évasion de Michael et des tensions à Fox River.",
              "thumbnail": "https://www.themoviedb.org/t/p/w454_and_h254_bestv2/yVa2L8mMjvRoKGrLUJxd0NxIkMy.jpg",
              "link": "https://uqload.cx/embed-jr32og9oklhc.html"
            },
            {
              "number": 4,
              "title": "Épisode 4",
              "duration": "43:00",
              "description": "Suite de l'évasion de Michael et des tensions à Fox River.",
              "thumbnail": "https://www.themoviedb.org/t/p/w454_and_h254_bestv2/yVa2L8mMjvRoKGrLUJxd0NxIkMy.jpg",
              "link": "https://uqload.cx/embed-jr32og9oklhc.html"
            },
            {
              "number": 5,
              "title": "Épisode 5",
              "duration": "43:00",
              "description": "Suite de l'évasion de Michael et des tensions à Fox River.",
              "thumbnail": "https://www.themoviedb.org/t/p/w454_and_h254_bestv2/yVa2L8mMjvRoKGrLUJxd0NxIkMy.jpg",
              "link": "https://uqload.cx/embed-jr32og9oklhc.html"
            },
            {
              "number": 6,
              "title": "Épisode 6",
              "duration": "43:00",
              "description": "Suite de l'évasion de Michael et des tensions à Fox River.",
              "thumbnail": "https://www.themoviedb.org/t/p/w454_and_h254_bestv2/yVa2L8mMjvRoKGrLUJxd0NxIkMy.jpg",
              "link": "https://uqload.cx/embed-jr32og9oklhc.html"
            },
            {
              "number": 7,
              "title": "Épisode 7",
              "duration": "43:00",
              "description": "Suite de l'évasion de Michael et des tensions à Fox River.",
              "thumbnail": "https://www.themoviedb.org/t/p/w454_and_h254_bestv2/yVa2L8mMjvRoKGrLUJxd0NxIkMy.jpg",
              "link": "https://uqload.cx/embed-jr32og9oklhc.html"
            },
            {
              "number": 8,
              "title": "Épisode 8",
              "duration": "43:00",
              "description": "Suite de l'évasion de Michael et des tensions à Fox River.",
              "thumbnail": "https://www.themoviedb.org/t/p/w454_and_h254_bestv2/yVa2L8mMjvRoKGrLUJxd0NxIkMy.jpg",
              "link": "https://uqload.cx/embed-jr32og9oklhc.html"
            },
            {
              "number": 9,
              "title": "Épisode 9",
              "duration": "43:00",
              "description": "Suite de l'évasion de Michael et des tensions à Fox River.",
              "thumbnail": "https://www.themoviedb.org/t/p/w454_and_h254_bestv2/yVa2L8mMjvRoKGrLUJxd0NxIkMy.jpg",
              "link": "https://uqload.cx/embed-jr32og9oklhc.html"
            },
            {
              "number": 10,
              "title": "Épisode 10",
              "duration": "43:00",
              "description": "Suite de l'évasion de Michael et des tensions à Fox River.",
              "thumbnail": "https://www.themoviedb.org/t/p/w454_and_h254_bestv2/yVa2L8mMjvRoKGrLUJxd0NxIkMy.jpg",
              "link": "https://uqload.cx/embed-jr32og9oklhc.html"
            },
            {
              "number": 11,
              "title": "Épisode 11",
              "duration": "43:00",
              "description": "Suite de l'évasion de Michael et des tensions à Fox River.",
              "thumbnail": "https://www.themoviedb.org/t/p/w454_and_h254_bestv2/yVa2L8mMjvRoKGrLUJxd0NxIkMy.jpg",
              "link": "https://uqload.cx/embed-jr32og9oklhc.html"
            },
            {
              "number": 12,
              "title": "Épisode 12",
              "duration": "43:00",
              "description": "Suite de l'évasion de Michael et des tensions à Fox River.",
              "thumbnail": "https://www.themoviedb.org/t/p/w454_and_h254_bestv2/yVa2L8mMjvRoKGrLUJxd0NxIkMy.jpg",
              "link": "https://uqload.cx/embed-jr32og9oklhc.html"
            },
            {
              "number": 13,
              "title": "Épisode 13",
              "duration": "43:00",
              "description": "Suite de l'évasion de Michael et des tensions à Fox River.",
              "thumbnail": "https://www.themoviedb.org/t/p/w454_and_h254_bestv2/yVa2L8mMjvRoKGrLUJxd0NxIkMy.jpg",
              "link": "https://uqload.cx/embed-jr32og9oklhc.html"
            },
            {
              "number": 14,
              "title": "Épisode 14",
              "duration": "43:00",
              "description": "Suite de l'évasion de Michael et des tensions à Fox River.",
              "thumbnail": "https://www.themoviedb.org/t/p/w454_and_h254_bestv2/yVa2L8mMjvRoKGrLUJxd0NxIkMy.jpg",
              "link": ""
            },
            {
              "number": 15,
              "title": "Épisode 15",
              "duration": "43:00",
              "description": "Suite de l'évasion de Michael et des tensions à Fox River.",
              "thumbnail": "https://www.themoviedb.org/t/p/w454_and_h254_bestv2/yVa2L8mMjvRoKGrLUJxd0NxIkMy.jpg",
              "link": ""
            },
            {
              "number": 16,
              "title": "Épisode 16",
              "duration": "43:00",
              "description": "Suite de l'évasion de Michael et des tensions à Fox River.",
              "thumbnail": "https://www.themoviedb.org/t/p/w454_and_h254_bestv2/yVa2L8mMjvRoKGrLUJxd0NxIkMy.jpg",
              "link": ""
            },
            {
              "number": 17,
              "title": "Épisode 17",
              "duration": "43:00",
              "description": "Suite de l'évasion de Michael et des tensions à Fox River.",
              "thumbnail": "https://www.themoviedb.org/t/p/w454_and_h254_bestv2/yVa2L8mMjvRoKGrLUJxd0NxIkMy.jpg",
              "link": ""
            },
            {
              "number": 18,
              "title": "Épisode 18",
              "duration": "43:00",
              "description": "Suite de l'évasion de Michael et des tensions à Fox River.",
              "thumbnail": "https://www.themoviedb.org/t/p/w454_and_h254_bestv2/yVa2L8mMjvRoKGrLUJxd0NxIkMy.jpg",
              "link": ""
            },
            {
              "number": 19,
              "title": "Épisode 19",
              "duration": "43:00",
              "description": "Suite de l'évasion de Michael et des tensions à Fox River.",
              "thumbnail": "https://www.themoviedb.org/t/p/w454_and_h254_bestv2/yVa2L8mMjvRoKGrLUJxd0NxIkMy.jpg",
              "link": ""
            },
            {
              "number": 20,
              "title": "Épisode 20",
              "duration": "43:00",
              "description": "Suite de l'évasion de Michael et des tensions à Fox River.",
              "thumbnail": "https://www.themoviedb.org/t/p/w454_and_h254_bestv2/yVa2L8mMjvRoKGrLUJxd0NxIkMy.jpg",
              "link": ""
            },
            {
              "number": 21,
              "title": "Épisode 21",
              "duration": "43:00",
              "description": "Suite de l'évasion de Michael et des tensions à Fox River.",
              "thumbnail": "https://www.themoviedb.org/t/p/w454_and_h254_bestv2/yVa2L8mMjvRoKGrLUJxd0NxIkMy.jpg",
              "link": ""
            },
            {
              "number": 22,
              "title": "Épisode 22",
              "duration": "43:00",
              "description": "Suite de l'évasion de Michael et des tensions à Fox River.",
              "thumbnail": "https://www.themoviedb.org/t/p/w454_and_h254_bestv2/yVa2L8mMjvRoKGrLUJxd0NxIkMy.jpg",
              "link": ""
            },
            {
              "number": 23,
              "title": "Épisode 23",
              "duration": "43:00",
              "description": "Suite de l'évasion de Michael et des tensions à Fox River.",
              "thumbnail": "https://www.themoviedb.org/t/p/w454_and_h254_bestv2/yVa2L8mMjvRoKGrLUJxd0NxIkMy.jpg",
              "link": ""
            },
            {
              "number": 24,
              "title": "Épisode 24",
              "duration": "43:00",
              "description": "Suite de l'évasion de Michael et des tensions à Fox River.",
              "thumbnail": "https://www.themoviedb.org/t/p/w454_and_h254_bestv2/yVa2L8mMjvRoKGrLUJxd0NxIkMy.jpg",
              "link": ""
            }
          ]
        },
        {
          "number": 5,
          "title": "Saison 5",
          "episodes": [
            {
              "number": 1,
              "title": "Épisode 1",
              "duration": "43:00",
              "description": "Suite de l'évasion de Michael et des tensions à Fox River.",
              "thumbnail": "https://www.themoviedb.org/t/p/w454_and_h254_bestv2/yVa2L8mMjvRoKGrLUJxd0NxIkMy.jpg",
              "link": ""
            },
            {
              "number": 2,
              "title": "Épisode 2",
              "duration": "43:00",
              "description": "Suite de l'évasion de Michael et des tensions à Fox River.",
              "thumbnail": "https://www.themoviedb.org/t/p/w454_and_h254_bestv2/yVa2L8mMjvRoKGrLUJxd0NxIkMy.jpg",
              "link": ""
            },
            {
              "number": 3,
              "title": "Épisode 3",
              "duration": "43:00",
              "description": "Suite de l'évasion de Michael et des tensions à Fox River.",
              "thumbnail": "https://www.themoviedb.org/t/p/w454_and_h254_bestv2/yVa2L8mMjvRoKGrLUJxd0NxIkMy.jpg",
              "link": ""
            },
            {
              "number": 4,
              "title": "Épisode 4",
              "duration": "43:00",
              "description": "Suite de l'évasion de Michael et des tensions à Fox River.",
              "thumbnail": "https://www.themoviedb.org/t/p/w454_and_h254_bestv2/yVa2L8mMjvRoKGrLUJxd0NxIkMy.jpg",
              "link": ""
            },
            {
              "number": 5,
              "title": "Épisode 5",
              "duration": "43:00",
              "description": "Suite de l'évasion de Michael et des tensions à Fox River.",
              "thumbnail": "https://www.themoviedb.org/t/p/w454_and_h254_bestv2/yVa2L8mMjvRoKGrLUJxd0NxIkMy.jpg",
              "link": ""
            },
            {
              "number": 6,
              "title": "Épisode 6",
              "duration": "43:00",
              "description": "Suite de l'évasion de Michael et des tensions à Fox River.",
              "thumbnail": "https://www.themoviedb.org/t/p/w454_and_h254_bestv2/yVa2L8mMjvRoKGrLUJxd0NxIkMy.jpg",
              "link": ""
            },
            {
              "number": 7,
              "title": "Épisode 7",
              "duration": "43:00",
              "description": "Suite de l'évasion de Michael et des tensions à Fox River.",
              "thumbnail": "https://www.themoviedb.org/t/p/w454_and_h254_bestv2/yVa2L8mMjvRoKGrLUJxd0NxIkMy.jpg",
              "link": ""
            },
            {
              "number": 8,
              "title": "Épisode 8",
              "duration": "43:00",
              "description": "Suite de l'évasion de Michael et des tensions à Fox River.",
              "thumbnail": "https://www.themoviedb.org/t/p/w454_and_h254_bestv2/yVa2L8mMjvRoKGrLUJxd0NxIkMy.jpg",
              "link": ""
            },
            {
              "number": 9,
              "title": "Épisode 9",
              "duration": "43:00",
              "description": "Suite de l'évasion de Michael et des tensions à Fox River.",
              "thumbnail": "https://www.themoviedb.org/t/p/w454_and_h254_bestv2/yVa2L8mMjvRoKGrLUJxd0NxIkMy.jpg",
              "link": ""
            }
          ]
        }
      ]
    },
    {
      "id": "m1",
      "type": "movie",
      "title": "Inception",
      "year": 2010,
      "description": "Dom Cobb est un voleur expérimenté, le meilleur dans l'art dangereux de l'extraction, voler les secrets les plus intimes enfouis au plus profond du subconscient pendant l'état de rêve.",
      "duration": "2h 28min",
      "poster": "https://www.themoviedb.org/t/p/w600_and_h900_bestv2/aej3LRUga5rhgkmRP6XMFw3ejbl.jpg",
      "backdrop": "https://www.themoviedb.org/t/p/original/s3TBrRGB1iav7gFOCNx3H31MoES.jpg",
      "link": ""
    }
  ]
}